ciclo/__init__.py
ciclo/callbacks.py
ciclo/logging.py
ciclo/loops/__init__.py
ciclo/loops/common.py
ciclo/loops/loop.py
ciclo/managed.py
ciclo/schedules.py
ciclo/states/__init__.py
ciclo/states/flax_state.py
ciclo/strategies.py
ciclo/timetracking.py
ciclo/types.py
ciclo/utils.py
ciclo-0.1.9.dist-info/LICENSE
ciclo-0.1.9.dist-info/METADATA
ciclo-0.1.9.dist-info/WHEEL
ciclo-0.1.9.dist-info/RECORD
